jupyterpilot/__init__.py
jupyterpilot/pysetup.py
jupyterpilot-1.0.0.dist-info/LICENSE.txt
jupyterpilot-1.0.0.dist-info/METADATA
jupyterpilot-1.0.0.dist-info/WHEEL
jupyterpilot-1.0.0.dist-info/top_level.txt
jupyterpilot-1.0.0.dist-info/RECORD
