Metadata-Version: 2.1
Name: jupyterpilot
Version: 1.0.0
Summary: Jupyter Pilot is a Python package that uses the OpenAI API to generate code from natural language prompts. It is designed to simplify the process of writing code and to make programming more accessible to non-programmers.
Home-page: https://github.com/ishu121992/JupyterPilot
Author: Eeshan
Author-email: Eeshan <mishra.eeshan@gmail.com>
License: : OSI Approved :: MIT License
Project-URL: Homepage, https://github.com/ishu121992/JupyterPilot
Project-URL: Bug Tracker, https://github.com/ishu121992/JupyterPilot/issues
Classifier: Programming Language :: Python :: 3
Classifier: License :: OSI Approved :: MIT License
Classifier: Operating System :: OS Independent
Requires-Python: >=3.7
License-File: LICENSE.txt
Requires-Dist: openai
